AnsiPrint/Error.py
AnsiPrint/__init__.py
AnsiPrint-0.0.7.dist-info/LICENSE
AnsiPrint-0.0.7.dist-info/METADATA
AnsiPrint-0.0.7.dist-info/WHEEL
AnsiPrint-0.0.7.dist-info/top_level.txt
AnsiPrint-0.0.7.dist-info/RECORD
